pytaravis/__init__.py
pytaravis-0.0.0.dist-info/METADATA
pytaravis-0.0.0.dist-info/WHEEL
pytaravis-0.0.0.dist-info/top_level.txt
pytaravis-0.0.0.dist-info/RECORD
